pyapple_mcp/__init__.py
pyapple_mcp/server.py
pyapple_mcp/setup_helper.py
pyapple_mcp/utils/__init__.py
pyapple_mcp/utils/applescript.py
pyapple_mcp/utils/calendar.py
pyapple_mcp/utils/contacts.py
pyapple_mcp/utils/mail.py
pyapple_mcp/utils/maps.py
pyapple_mcp/utils/messages.py
pyapple_mcp/utils/notes.py
pyapple_mcp/utils/reminders.py
pyapple_mcp/utils/websearch.py
pyapple_mcp-1.0.2.dist-info/licenses/LICENSE
pyapple_mcp-1.0.2.dist-info/METADATA
pyapple_mcp-1.0.2.dist-info/WHEEL
pyapple_mcp-1.0.2.dist-info/entry_points.txt
pyapple_mcp-1.0.2.dist-info/top_level.txt
pyapple_mcp-1.0.2.dist-info/RECORD
