Metadata-Version: 2.4
Name: pyapple-mcp
Version: 1.0.2
Summary: Python implementation of Apple MCP tools for macOS
Author-email: Steven Yu <pyapple-mcp@example.com>
License-Expression: MIT
Project-URL: Homepage, https://54yyyu.github.io/pyapple-mcp/
Project-URL: Repository, https://github.com/54yyyu/pyapple-mcp
Project-URL: Issues, https://github.com/54yyyu/pyapple-mcp/issues
Project-URL: Documentation, https://54yyyu.github.io/pyapple-mcp/api.html
Keywords: mcp,model-context-protocol,apple,macos,automation,applescript
Classifier: Development Status :: 4 - Beta
Classifier: Intended Audience :: Developers
Classifier: Programming Language :: Python :: 3
Classifier: Programming Language :: Python :: 3.10
Classifier: Programming Language :: Python :: 3.11
Classifier: Programming Language :: Python :: 3.12
Classifier: Operating System :: MacOS
Requires-Python: >=3.10
License-File: LICENSE
Requires-Dist: mcp>=1.0.0
Requires-Dist: httpx>=0.25.0
Requires-Dist: beautifulsoup4>=4.12.0
Requires-Dist: pyobjc-framework-Cocoa>=10.0
Requires-Dist: pyobjc-framework-AddressBook>=10.0
Requires-Dist: pyobjc-framework-EventKit>=10.0
Requires-Dist: pyobjc-framework-ScriptingBridge>=10.0
Requires-Dist: pyobjc-framework-MapKit>=10.0
Provides-Extra: dev
Requires-Dist: pytest>=7.0.0; extra == "dev"
Requires-Dist: pytest-asyncio>=0.21.0; extra == "dev"
Requires-Dist: black>=23.0.0; extra == "dev"
Requires-Dist: isort>=5.12.0; extra == "dev"
Requires-Dist: mypy>=1.5.0; extra == "dev"
Dynamic: license-file
